filedust/__init__.py
filedust/cli.py
filedust/junk.py
filedust-0.4.1.dist-info/LICENCE
filedust-0.4.1.dist-info/METADATA
filedust-0.4.1.dist-info/WHEEL
filedust-0.4.1.dist-info/entry_points.txt
filedust-0.4.1.dist-info/RECORD
