Metadata-Version: 2.1
Name: filedust
Version: 0.4.1
Summary: Opinionated junk cleaner for dev machines (caches, build artifacts, editor backups).
Home-page: https://git.sysmd.uk/guardutils/filedust
License: GPL-3.0-or-later
Author: Marco D'Aleo
Author-email: marco@marcodaleo.com
Requires-Python: >=3.10,<4.0
Classifier: License :: OSI Approved :: GNU General Public License v3 or later (GPLv3+)
Classifier: Programming Language :: Python :: 3
Classifier: Programming Language :: Python :: 3.10
Classifier: Programming Language :: Python :: 3.11
Classifier: Programming Language :: Python :: 3.12
Classifier: Programming Language :: Python :: 3.13
Requires-Dist: argcomplete (>=2)
Requires-Dist: rich (>=12)
Project-URL: Repository, https://git.sysmd.uk/guardutils/filedust
